<?xml version="1.0" encoding="UTF-8"?>
<T3locallangExt>
  <data type="array">
    <languageKey index="ru" type="array">
			<label index="About">Сведения</label>
			<label index="About HTMLArea">Информация о htmlArea RTE</label>
			<label index="Absbottom">Строка по низу</label>
			<label index="Absmiddle">Строка по центру</label>
			<label index="Alignment:">Выравнивание текста:</label>
			<label index="Alignment not set">Не установлено</label>
			<label index="All rights reserved.">Все права защищены</label>
			<label index="Alternate text:">Альтернативный текст (ALT):</label>
			<label index="Baseline">По базовой линии</label>
			<label index="Block style label">Стиль блока:</label>
			<label index="Border">Рамка</label>
			<label index="Border thickness:">Толщина рамки:</label>
			<label index="Bottom">Текст по низу</label>
			<label index="Browser support">Поддержка браузеров</label>
			<label index="Cancel">Отмена</label>
			<label index="Cell padding:">Отступы внутри ячейки</label>
			<label index="Cell spacing:">Интервал между ячейками:</label>
			<label index="Center">По центру</label>
			<label index="Close">Закрыть</label>
			<label index="Cols:">Столбцы:</label>
			<label index="Delete">Удалить</label>
			<label index="Developer">Разработчик</label>
			<label index="Dimension">Размерность</label>
			<label index="Em">Em</label>
			<label index="Enter the image URL here">Введите URL адрес картинки</label>
			<label index="Float:">Плавающее:</label>
			<label index="For browsers that dont support images">Для браузеров, которые не поддерживают изображений</label>
			<label index="free_editor">Бесплатный редактор с открытым кодом для полей &lt;textarea&gt;, встроенный в TYPO3.</label>
			<label index="General">Общее</label>
			<label index="Horizontal:">Горизонтальные:</label>
			<label index="Horizontal padding">Отступ по горизонтали</label>
			<label index="htmlArea License (based on BSD license)">Лицензия htmlArea RTE (на основе лицензии BSD)</label>
			<label index="Image alignment:">Выравнивание изображения:</label>
			<label index="Image Preview">Предварительный просмотр изображения</label>
			<label index="Image URL:">URL изображения:</label>
			<label index="image_url_first">Сначала необходимо указать URL изображения</label>
			<label index="image_url_required">Нужно ввести URL изображения</label>
			<label index="Insert Custom Element">Вставить дополнительный элемент</label>
			<label index="Insert image">Вставить изображение</label>
			<label index="Insert Image">Вставить/заменить изображение</label>
			<label index="Insert link">Вставить ссылку</label>
			<label index="Insert/Modify Acronym">Вставить/изменить акроним или аббревиатуру</label>
			<label index="Insert/Modify Link">Вставить/изменить ссылку</label>
			<label index="Insert Table">Вставить таблицу</label>
			<label index="Justify">Выравнивание</label>
			<label index="Language">Язык</label>
			<label index="Language:">Язык:</label>
			<label index="Layout">Шаблон</label>
			<label index="Leave empty for no border">Оставьте пустым, если рамка не нужна</label>
			<label index="Left">Влево</label>
			<label index="LeftToRight">Слева направо</label>
			<label index="License">Лицензия</label>
			<label index="link_href_tooltip">Введите URL ссылки</label>
			<label index="link_target_tooltip">Выберите название фрейма в который будет вести данная ссылка</label>
			<label index="link_title_tooltip">Введите всплывающую подсказку для ссылки</label>
			<label index="link_url_required">Пожалуйста, введите адрес (URL), на который указывает эта ссылка</label>
			<label index="Middle">По центру</label>
			<label index="Modify image">Изменить изображение</label>
			<label index="Modify link">Изменить ссылку</label>
			<label index="Mozilla_or_IE">Для браузеров Firefox 1.5+, SeaMonkey 1.0+, Safari 3.0.4+, Google Chrome 1.0+ и Opera 9.62+ любой из ОС, а также для Internet Explorer 6.0+ для Windows.</label>
			<label index="Name">Название</label>
			<label index="No language mark">Нет языка</label>
			<label index="Non-floating">Не плавающее</label>
			<label index="No plugins have been loaded.">Дополнения не загружены.</label>
			<label index="Not set">Не установлено</label>
			<label index="Number of columns">Количество столбцов</label>
			<label index="Number of rows">Количество строк</label>
			<label index="OK">ОК</label>
			<label index="Percent">Проценты</label>
			<label index="Pixels">Точки</label>
			<label index="Plugins">Дополнения</label>
			<label index="Positioning of this image">Выравнивание изображения относительно текста</label>
			<label index="Preview">Предварительный просмотр</label>
			<label index="Preview the image in a new window">Предпросмотр изображения в новом окне</label>
			<label index="product_documentation">Подробная информация доступна по адресу:</label>
			<label index="Remove language mark">Удалить язык</label>
			<label index="Right">Вправо</label>
			<label index="RightToLeft">Справа налево</label>
			<label index="Rows:">Строки:</label>
			<label index="Select Color">Выбор цвета</label>
			<label index="Space between adjacent cells">Расстояние между смежными ячейками</label>
			<label index="Space between content and border in cell">Отступы между содержимым ячейки и её рамкой</label>
			<label index="Spacing and padding">Интервалы и отступы (внешние и внутри)</label>
			<label index="Sponsored by">Оплачивается</label>
			<label index="statusBarReady">Готово</label>
			<label index="statusBarStyle">Стиль</label>
			<label index="style">Параграф:</label>
			<label index="Target:">Цель:</label>
			<label index="target_blank">Новое окно (_blank)</label>
			<label index="target_none">Пусто (значение наследуется)</label>
			<label index="target_other">Другой фрейм</label>
			<label index="target_self">Тот же фрейм (_self)</label>
			<label index="target_top">Основной фрейм (_top)</label>
			<label index="Text alignment">Выравнивание текста</label>
			<label index="Text direction">Направление текста</label>
			<label index="Text direction:">Направление текста:</label>
			<label index="text_style">Стиль текста:</label>
			<label index="Texttop">Текст по верху</label>
			<label index="The following plugins have been loaded.">Загружены следующие дополнения.</label>
			<label index="Title (tooltip):">Заголовок:</label>
			<label index="Top">Верх</label>
			<label index="URL:">Адрес</label>
			<label index="User agent reports:">Сообщения браузера:</label>
			<label index="Vertical:">Вертикальные</label>
			<label index="Vertical padding">Отступ по вертикали</label>
			<label index="Where the image should float">Должно ли изображение быть плавающим?</label>
			<label index="Where the table should float">Должна ли таблица быть плавающей?</label>
			<label index="Width:">Ширина:</label>
			<label index="Width of the table">Ширина таблицы</label>
			<label index="Width unit">Единицы ширины</label>
			<label index="word">слово</label>
			<label index="words">слова</label>
			<label index="You must enter a number of columns">Необходимо ввести количество столбцов</label>
			<label index="You must enter a number of rows">Необходимо ввести количество строк</label>
		</languageKey>
  </data>
</T3locallangExt>
